wunlatex/__init__.py
wunlatex/components.py
wunlatex/document.py
wunlatex/legacy_document.py
wunlatex/templates/template.tex
wunlatex/utils.py
wunlatex-0.1.2.dist-info/LICENSE
wunlatex-0.1.2.dist-info/METADATA
wunlatex-0.1.2.dist-info/WHEEL
wunlatex-0.1.2.dist-info/RECORD
