Metadata-Version: 2.1
Name: wunlatex
Version: 0.1.2
Summary: Write LaTeX documents
License: MIT
Author: Philippe Lacroix-Ouellette
Author-email: philippe.lacroix.ouellette@gmail.com
Requires-Python: >=3.11,<3.12
Classifier: License :: OSI Approved :: MIT License
Classifier: Programming Language :: Python :: 3
Classifier: Programming Language :: Python :: 3.11
Requires-Dist: pandas (>=2.1.1,<3.0.0)
Requires-Dist: pytest (>=7.4.3,<8.0.0)
Requires-Dist: wuncolors (>=0.1.0,<0.2.0)
